googlesearch/__init__.py
googlesearch/models.py
googlesearch/news.py
googlesearch/search.py
googlesearch/settings.py
googlesearch/utils.py
googlesearch/resources/all_domain.txt
googlesearch_tool-2.0.0.dist-info/METADATA
googlesearch_tool-2.0.0.dist-info/WHEEL
googlesearch_tool-2.0.0.dist-info/licenses/LICENSE.txt
googlesearch_tool-2.0.0.dist-info/RECORD
