Metadata-Version: 2.4
Name: googlesearch-tool
Version: 2.0.0
Summary: A Python library for performing Google searches with Opera Mini UA bypass
Project-URL: Homepage, https://github.com/huazz233/googlesearch
Project-URL: Documentation, https://github.com/huazz233/googlesearch#readme
Project-URL: Repository, https://github.com/huazz233/googlesearch
Project-URL: Issues, https://github.com/huazz233/googlesearch/issues
Author-email: huazz233 <huazz233@163.com>
License-Expression: MIT
License-File: LICENSE.txt
Keywords: async,google,opera-mini,proxy,search,web-scraping
Classifier: Development Status :: 4 - Beta
Classifier: Intended Audience :: Developers
Classifier: License :: OSI Approved :: MIT License
Classifier: Operating System :: OS Independent
Classifier: Programming Language :: Python :: 3
Classifier: Programming Language :: Python :: 3.8
Classifier: Programming Language :: Python :: 3.9
Classifier: Programming Language :: Python :: 3.10
Classifier: Programming Language :: Python :: 3.11
Classifier: Programming Language :: Python :: 3.12
Classifier: Topic :: Internet :: WWW/HTTP :: Indexing/Search
Classifier: Topic :: Software Development :: Libraries :: Python Modules
Requires-Python: >=3.8
Requires-Dist: beautifulsoup4>=4.9.3
Requires-Dist: httpx>=0.24.0
Provides-Extra: dev
Requires-Dist: pytest-asyncio>=0.21.0; extra == 'dev'
Requires-Dist: pytest>=7.0.0; extra == 'dev'
